nmmo/__init__.py
nmmo/_version.py
nmmo/infrastructure.py
nmmo/overlay.py
nmmo/scripting.py
nmmo/version.py
nmmo/websocket.py
nmmo/core/__init__.py
nmmo/core/agent.py
nmmo/core/config.py
nmmo/core/env.py
nmmo/core/map.py
nmmo/core/realm.py
nmmo/core/terrain.py
nmmo/core/tile.py
nmmo/entity/__init__.py
nmmo/entity/entity.py
nmmo/entity/npc.py
nmmo/entity/player.py
nmmo/lib/__init__.py
nmmo/lib/colors.py
nmmo/lib/log.py
nmmo/lib/material.py
nmmo/lib/overlay.py
nmmo/lib/priorityqueue.py
nmmo/lib/utils.py
nmmo/systems/__init__.py
nmmo/systems/achievement.py
nmmo/systems/combat.py
nmmo/systems/droptable.py
nmmo/systems/equipment.py
nmmo/systems/experience.py
nmmo/systems/skill.py
nmmo/systems/ai/__init__.py
nmmo/systems/ai/attack.py
nmmo/systems/ai/behavior.py
nmmo/systems/ai/dynamic_programming.py
nmmo/systems/ai/move.py
nmmo/systems/ai/policy.py
nmmo/systems/ai/utils.py
nmmo-1.5.3.2.dist-info/LICENSE
nmmo-1.5.3.2.dist-info/METADATA
nmmo-1.5.3.2.dist-info/WHEEL
nmmo-1.5.3.2.dist-info/top_level.txt
nmmo-1.5.3.2.dist-info/RECORD
